{
  "n_nodes": 61,
  "nodes": [
    {
      "id": 0,
      "label": "0_Indianapolis_",
      "x": -86.15804,
      "y": 39.76838
    },
    {
      "id": 1,
      "label": "1_Bloomington",
      "x": -86.52639,
      "y": 39.16532
    },
    {
      "id": 2,
      "label": "2_Shelbyville",
      "x": -85.77692,
      "y": 39.52144
    },
    {
      "id": 3,
      "label": "3_Greenwood",
      "x": -86.10665,
      "y": 39.61366
    },
    {
      "id": 4,
      "label": "5_Centralia_",
      "x": -89.1334,
      "y": 38.52505
    },
    {
      "id": 5,
      "label": "6_Columbus",
      "x": -85.92138,
      "y": 39.20144
    },
    {
      "id": 6,
      "label": "7_Louisville",
      "x": -85.75941,
      "y": 38.25424
    },
    {
      "id": 7,
      "label": "8_Lansing",
      "x": -84.55553,
      "y": 42.73254
    },
    {
      "id": 8,
      "label": "9_Jackson",
      "x": -84.40135,
      "y": 42.24587
    },
    {
      "id": 9,
      "label": "10_St_Loius",
      "x": -90.19789,
      "y": 38.62727
    },
    {
      "id": 10,
      "label": "11_Lafayette",
      "x": -86.87529,
      "y": 40.4167
    },
    {
      "id": 11,
      "label": "12_Grand_Rapids",
      "x": -85.66809,
      "y": 42.96336
    },
    {
      "id": 12,
      "label": "13_Muskegon",
      "x": -86.24839,
      "y": 43.23418
    },
    {
      "id": 13,
      "label": "14_Gary",
      "x": -87.34643,
      "y": 41.59337
    },
    {
      "id": 14,
      "label": "15_Battle_Creek",
      "x": -85.17971,
      "y": 42.32115
    },
    {
      "id": 15,
      "label": "16_Rockford_",
      "x": -89.094,
      "y": 42.27113
    },
    {
      "id": 16,
      "label": "17_Madison_",
      "x": -89.40123,
      "y": 43.07305
    },
    {
      "id": 17,
      "label": "18_Muncie",
      "x": -85.38636,
      "y": 40.19338
    },
    {
      "id": 18,
      "label": "19_Anderson",
      "x": -85.68025,
      "y": 40.10532
    },
    {
      "id": 19,
      "label": "20_Mattoon_",
      "x": -88.37283,
      "y": 39.48309
    },
    {
      "id": 20,
      "label": "21_Terre_Haute_",
      "x": -87.41391,
      "y": 39.4667
    },
    {
      "id": 21,
      "label": "22_Champaign_",
      "x": -88.24338,
      "y": 40.11642
    },
    {
      "id": 22,
      "label": "23_Bloomington",
      "x": -88.99369,
      "y": 40.4842
    },
    {
      "id": 23,
      "label": "24_Peoria_",
      "x": -89.58899,
      "y": 40.69365
    },
    {
      "id": 24,
      "label": "25_Springfield_",
      "x": -89.64371,
      "y": 39.80172
    },
    {
      "id": 25,
      "label": "26_Ann_Arbor",
      "x": -83.74088,
      "y": 42.27756
    },
    {
      "id": 26,
      "label": "27_Traverse_City",
      "x": -85.62063,
      "y": 44.76306
    },
    {
      "id": 27,
      "label": "28_Mt_Pleasant",
      "x": -84.76751,
      "y": 43.59781
    },
    {
      "id": 28,
      "label": "29_Portage",
      "x": -87.17615,
      "y": 41.57587
    },
    {
      "id": 29,
      "label": "30_Chicago_",
      "x": -87.65005,
      "y": 41.85003
    },
    {
      "id": 30,
      "label": "31_Midland",
      "x": -84.24721,
      "y": 43.61558
    },
    {
      "id": 31,
      "label": "32_None",
      "x": 0.0,
      "y": 0.0
    },
    {
      "id": 32,
      "label": "33_Saginaw",
      "x": -83.95081,
      "y": 43.41947
    },
    {
      "id": 33,
      "label": "34_None",
      "x": 0.0,
      "y": 0.0
    },
    {
      "id": 34,
      "label": "35_Appleton_",
      "x": -88.41538,
      "y": 44.26193
    },
    {
      "id": 35,
      "label": "36_Oshkosh_",
      "x": -88.54261,
      "y": 44.02471
    },
    {
      "id": 36,
      "label": "37_Milwaukee_",
      "x": -87.90647,
      "y": 43.0389
    },
    {
      "id": 37,
      "label": "38_Green_Bay_",
      "x": -88.01983,
      "y": 44.51916
    },
    {
      "id": 38,
      "label": "39_Des_Plaines_",
      "x": -87.8834,
      "y": 42.03336
    },
    {
      "id": 39,
      "label": "40_Northbrook_",
      "x": -87.82895,
      "y": 42.12753
    },
    {
      "id": 40,
      "label": "41_La_Grange",
      "x": -87.86923,
      "y": 41.80503
    },
    {
      "id": 41,
      "label": "42_Oak_Brook_",
      "x": -87.92895,
      "y": 41.83281
    },
    {
      "id": 42,
      "label": "43_Lima",
      "x": -84.10523,
      "y": 40.74255
    },
    {
      "id": 43,
      "label": "44_Fort_Wayne",
      "x": -85.12886,
      "y": 41.1306
    },
    {
      "id": 44,
      "label": "45_South_Bend",
      "x": -86.25001,
      "y": 41.68338
    },
    {
      "id": 45,
      "label": "46_Warsaw",
      "x": -85.85305,
      "y": 41.2381
    },
    {
      "id": 46,
      "label": "47_Marion",
      "x": -85.6597,
      "y": 40.54969
    },
    {
      "id": 47,
      "label": "48_Kokomo",
      "x": -86.1336,
      "y": 40.48643
    },
    {
      "id": 48,
      "label": "49_Elkhart",
      "x": -85.97667,
      "y": 41.68199
    },
    {
      "id": 49,
      "label": "50_Three_Rivers",
      "x": -85.63249,
      "y": 41.94394
    },
    {
      "id": 50,
      "label": "51_Kalamazoo",
      "x": -85.58723,
      "y": 42.29171
    },
    {
      "id": 51,
      "label": "52_Niles",
      "x": -86.25418,
      "y": 41.82977
    },
    {
      "id": 52,
      "label": "53_Dayton_",
      "x": -84.19161,
      "y": 39.75895
    },
    {
      "id": 53,
      "label": "54_Cincinnati_",
      "x": -84.45689,
      "y": 39.162
    },
    {
      "id": 54,
      "label": "55_Saginaw",
      "x": -83.95081,
      "y": 43.41947
    },
    {
      "id": 55,
      "label": "56_Flint",
      "x": -83.68746,
      "y": 43.01253
    },
    {
      "id": 56,
      "label": "57_Pontiac",
      "x": -83.29105,
      "y": 42.63892
    },
    {
      "id": 57,
      "label": "58_Southfield/Detroit",
      "x": -83.2428,
      "y": 42.4762
    },
    {
      "id": 58,
      "label": "59_Toledo",
      "x": -83.55521,
      "y": 41.66394
    },
    {
      "id": 59,
      "label": "60_Cleveland",
      "x": -81.69541,
      "y": 41.4995
    },
    {
      "id": 60,
      "label": "62_Columbus_",
      "x": -82.99879,
      "y": 39.96118
    }
  ],
  "n_edges": 158,
  "edges": [
    {
      "id": 0,
      "label": "edge_0",
      "src": 0,
      "dst": 3,
      "weight": 10,
      "bw": 1000000,
      "delay": 34
    },
    {
      "id": 1,
      "label": "edge_1",
      "src": 3,
      "dst": 0,
      "weight": 10,
      "bw": 1000000,
      "delay": 34
    },
    {
      "id": 2,
      "label": "edge_2",
      "src": 0,
      "dst": 10,
      "weight": 10,
      "bw": 1000000,
      "delay": 162
    },
    {
      "id": 3,
      "label": "edge_3",
      "src": 10,
      "dst": 0,
      "weight": 10,
      "bw": 1000000,
      "delay": 162
    },
    {
      "id": 4,
      "label": "edge_4",
      "src": 0,
      "dst": 2,
      "weight": 10,
      "bw": 1000000,
      "delay": 76
    },
    {
      "id": 5,
      "label": "edge_5",
      "src": 2,
      "dst": 0,
      "weight": 10,
      "bw": 1000000,
      "delay": 76
    },
    {
      "id": 6,
      "label": "edge_6",
      "src": 0,
      "dst": 18,
      "weight": 10,
      "bw": 1000000,
      "delay": 97
    },
    {
      "id": 7,
      "label": "edge_7",
      "src": 18,
      "dst": 0,
      "weight": 10,
      "bw": 1000000,
      "delay": 97
    },
    {
      "id": 8,
      "label": "edge_8",
      "src": 0,
      "dst": 20,
      "weight": 10,
      "bw": 1000000,
      "delay": 192
    },
    {
      "id": 9,
      "label": "edge_9",
      "src": 20,
      "dst": 0,
      "weight": 10,
      "bw": 1000000,
      "delay": 192
    },
    {
      "id": 10,
      "label": "edge_10",
      "src": 1,
      "dst": 3,
      "weight": 10,
      "bw": 1000000,
      "delay": 107
    },
    {
      "id": 11,
      "label": "edge_11",
      "src": 3,
      "dst": 1,
      "weight": 10,
      "bw": 1000000,
      "delay": 107
    },
    {
      "id": 12,
      "label": "edge_12",
      "src": 1,
      "dst": 5,
      "weight": 10,
      "bw": 1000000,
      "delay": 92
    },
    {
      "id": 13,
      "label": "edge_13",
      "src": 5,
      "dst": 1,
      "weight": 10,
      "bw": 1000000,
      "delay": 92
    },
    {
      "id": 14,
      "label": "edge_14",
      "src": 2,
      "dst": 53,
      "weight": 10,
      "bw": 1000000,
      "delay": 205
    },
    {
      "id": 15,
      "label": "edge_15",
      "src": 53,
      "dst": 2,
      "weight": 10,
      "bw": 1000000,
      "delay": 205
    },
    {
      "id": 16,
      "label": "edge_16",
      "src": 2,
      "dst": 5,
      "weight": 10,
      "bw": 1000000,
      "delay": 67
    },
    {
      "id": 17,
      "label": "edge_17",
      "src": 5,
      "dst": 2,
      "weight": 10,
      "bw": 1000000,
      "delay": 67
    },
    {
      "id": 18,
      "label": "edge_18",
      "src": 4,
      "dst": 9,
      "weight": 10,
      "bw": 1000000,
      "delay": 160
    },
    {
      "id": 19,
      "label": "edge_19",
      "src": 9,
      "dst": 4,
      "weight": 10,
      "bw": 1000000,
      "delay": 160
    },
    {
      "id": 20,
      "label": "edge_20",
      "src": 4,
      "dst": 19,
      "weight": 10,
      "bw": 1000000,
      "delay": 213
    },
    {
      "id": 21,
      "label": "edge_21",
      "src": 19,
      "dst": 4,
      "weight": 10,
      "bw": 1000000,
      "delay": 213
    },
    {
      "id": 22,
      "label": "edge_22",
      "src": 5,
      "dst": 6,
      "weight": 10,
      "bw": 1000000,
      "delay": 181
    },
    {
      "id": 23,
      "label": "edge_23",
      "src": 6,
      "dst": 5,
      "weight": 10,
      "bw": 1000000,
      "delay": 181
    },
    {
      "id": 24,
      "label": "edge_24",
      "src": 7,
      "dst": 55,
      "weight": 10,
      "bw": 1000000,
      "delay": 133
    },
    {
      "id": 25,
      "label": "edge_25",
      "src": 55,
      "dst": 7,
      "weight": 10,
      "bw": 1000000,
      "delay": 133
    },
    {
      "id": 26,
      "label": "edge_26",
      "src": 7,
      "dst": 8,
      "weight": 10,
      "bw": 1000000,
      "delay": 97
    },
    {
      "id": 27,
      "label": "edge_27",
      "src": 8,
      "dst": 7,
      "weight": 10,
      "bw": 1000000,
      "delay": 97
    },
    {
      "id": 28,
      "label": "edge_28",
      "src": 7,
      "dst": 27,
      "weight": 10,
      "bw": 1000000,
      "delay": 167
    },
    {
      "id": 29,
      "label": "edge_29",
      "src": 27,
      "dst": 7,
      "weight": 10,
      "bw": 1000000,
      "delay": 167
    },
    {
      "id": 30,
      "label": "edge_30",
      "src": 7,
      "dst": 11,
      "weight": 10,
      "bw": 1000000,
      "delay": 161
    },
    {
      "id": 31,
      "label": "edge_31",
      "src": 11,
      "dst": 7,
      "weight": 10,
      "bw": 1000000,
      "delay": 161
    },
    {
      "id": 32,
      "label": "edge_32",
      "src": 8,
      "dst": 25,
      "weight": 10,
      "bw": 1000000,
      "delay": 95
    },
    {
      "id": 33,
      "label": "edge_33",
      "src": 25,
      "dst": 8,
      "weight": 10,
      "bw": 1000000,
      "delay": 95
    },
    {
      "id": 34,
      "label": "edge_34",
      "src": 8,
      "dst": 14,
      "weight": 10,
      "bw": 1000000,
      "delay": 112
    },
    {
      "id": 35,
      "label": "edge_35",
      "src": 14,
      "dst": 8,
      "weight": 10,
      "bw": 1000000,
      "delay": 112
    },
    {
      "id": 36,
      "label": "edge_36",
      "src": 9,
      "dst": 24,
      "weight": 10,
      "bw": 1000000,
      "delay": 236
    },
    {
      "id": 37,
      "label": "edge_37",
      "src": 24,
      "dst": 9,
      "weight": 10,
      "bw": 1000000,
      "delay": 236
    },
    {
      "id": 38,
      "label": "edge_38",
      "src": 10,
      "dst": 47,
      "weight": 10,
      "bw": 1000000,
      "delay": 110
    },
    {
      "id": 39,
      "label": "edge_39",
      "src": 47,
      "dst": 10,
      "weight": 10,
      "bw": 1000000,
      "delay": 110
    },
    {
      "id": 40,
      "label": "edge_40",
      "src": 10,
      "dst": 13,
      "weight": 10,
      "bw": 1000000,
      "delay": 232
    },
    {
      "id": 41,
      "label": "edge_41",
      "src": 13,
      "dst": 10,
      "weight": 10,
      "bw": 1000000,
      "delay": 232
    },
    {
      "id": 42,
      "label": "edge_42",
      "src": 11,
      "dst": 50,
      "weight": 10,
      "bw": 1000000,
      "delay": 129
    },
    {
      "id": 43,
      "label": "edge_43",
      "src": 50,
      "dst": 11,
      "weight": 10,
      "bw": 1000000,
      "delay": 129
    },
    {
      "id": 44,
      "label": "edge_44",
      "src": 11,
      "dst": 12,
      "weight": 10,
      "bw": 1000000,
      "delay": 98
    },
    {
      "id": 45,
      "label": "edge_45",
      "src": 12,
      "dst": 11,
      "weight": 10,
      "bw": 1000000,
      "delay": 98
    },
    {
      "id": 46,
      "label": "edge_46",
      "src": 12,
      "dst": 27,
      "weight": 10,
      "bw": 1000000,
      "delay": 215
    },
    {
      "id": 47,
      "label": "edge_47",
      "src": 27,
      "dst": 12,
      "weight": 10,
      "bw": 1000000,
      "delay": 215
    },
    {
      "id": 48,
      "label": "edge_48",
      "src": 12,
      "dst": 26,
      "weight": 10,
      "bw": 1000000,
      "delay": 300
    },
    {
      "id": 49,
      "label": "edge_49",
      "src": 26,
      "dst": 12,
      "weight": 10,
      "bw": 1000000,
      "delay": 300
    },
    {
      "id": 50,
      "label": "edge_50",
      "src": 13,
      "dst": 40,
      "weight": 10,
      "bw": 1000000,
      "delay": 87
    },
    {
      "id": 51,
      "label": "edge_51",
      "src": 40,
      "dst": 13,
      "weight": 10,
      "bw": 1000000,
      "delay": 87
    },
    {
      "id": 52,
      "label": "edge_52",
      "src": 14,
      "dst": 50,
      "weight": 10,
      "bw": 1000000,
      "delay": 61
    },
    {
      "id": 53,
      "label": "edge_53",
      "src": 50,
      "dst": 14,
      "weight": 10,
      "bw": 1000000,
      "delay": 61
    },
    {
      "id": 54,
      "label": "edge_54",
      "src": 15,
      "dst": 16,
      "weight": 10,
      "bw": 1000000,
      "delay": 159
    },
    {
      "id": 55,
      "label": "edge_55",
      "src": 16,
      "dst": 15,
      "weight": 10,
      "bw": 1000000,
      "delay": 159
    },
    {
      "id": 56,
      "label": "edge_56",
      "src": 15,
      "dst": 41,
      "weight": 10,
      "bw": 1000000,
      "delay": 184
    },
    {
      "id": 57,
      "label": "edge_57",
      "src": 41,
      "dst": 15,
      "weight": 10,
      "bw": 1000000,
      "delay": 184
    },
    {
      "id": 58,
      "label": "edge_58",
      "src": 16,
      "dst": 35,
      "weight": 10,
      "bw": 1000000,
      "delay": 215
    },
    {
      "id": 59,
      "label": "edge_59",
      "src": 35,
      "dst": 16,
      "weight": 10,
      "bw": 1000000,
      "delay": 215
    },
    {
      "id": 60,
      "label": "edge_60",
      "src": 16,
      "dst": 36,
      "weight": 10,
      "bw": 1000000,
      "delay": 207
    },
    {
      "id": 61,
      "label": "edge_61",
      "src": 36,
      "dst": 16,
      "weight": 10,
      "bw": 1000000,
      "delay": 207
    },
    {
      "id": 62,
      "label": "edge_62",
      "src": 17,
      "dst": 18,
      "weight": 10,
      "bw": 1000000,
      "delay": 49
    },
    {
      "id": 63,
      "label": "edge_63",
      "src": 18,
      "dst": 17,
      "weight": 10,
      "bw": 1000000,
      "delay": 49
    },
    {
      "id": 64,
      "label": "edge_64",
      "src": 17,
      "dst": 46,
      "weight": 10,
      "bw": 1000000,
      "delay": 81
    },
    {
      "id": 65,
      "label": "edge_65",
      "src": 46,
      "dst": 17,
      "weight": 10,
      "bw": 1000000,
      "delay": 81
    },
    {
      "id": 66,
      "label": "edge_66",
      "src": 19,
      "dst": 21,
      "weight": 10,
      "bw": 1000000,
      "delay": 123
    },
    {
      "id": 67,
      "label": "edge_67",
      "src": 21,
      "dst": 19,
      "weight": 10,
      "bw": 1000000,
      "delay": 123
    },
    {
      "id": 68,
      "label": "edge_68",
      "src": 19,
      "dst": 20,
      "weight": 10,
      "bw": 1000000,
      "delay": 142
    },
    {
      "id": 69,
      "label": "edge_69",
      "src": 20,
      "dst": 19,
      "weight": 10,
      "bw": 1000000,
      "delay": 142
    },
    {
      "id": 70,
      "label": "edge_70",
      "src": 21,
      "dst": 31,
      "weight": 10,
      "bw": 1000000,
      "delay": 127
    },
    {
      "id": 71,
      "label": "edge_71",
      "src": 31,
      "dst": 21,
      "weight": 10,
      "bw": 1000000,
      "delay": 127
    },
    {
      "id": 72,
      "label": "edge_72",
      "src": 22,
      "dst": 31,
      "weight": 10,
      "bw": 1000000,
      "delay": 127
    },
    {
      "id": 73,
      "label": "edge_73",
      "src": 31,
      "dst": 22,
      "weight": 10,
      "bw": 1000000,
      "delay": 127
    },
    {
      "id": 74,
      "label": "edge_74",
      "src": 22,
      "dst": 23,
      "weight": 10,
      "bw": 1000000,
      "delay": 97
    },
    {
      "id": 75,
      "label": "edge_75",
      "src": 23,
      "dst": 22,
      "weight": 10,
      "bw": 1000000,
      "delay": 97
    },
    {
      "id": 76,
      "label": "edge_76",
      "src": 23,
      "dst": 24,
      "weight": 10,
      "bw": 1000000,
      "delay": 170
    },
    {
      "id": 77,
      "label": "edge_77",
      "src": 24,
      "dst": 23,
      "weight": 10,
      "bw": 1000000,
      "delay": 170
    },
    {
      "id": 78,
      "label": "edge_78",
      "src": 24,
      "dst": 31,
      "weight": 10,
      "bw": 1000000,
      "delay": 127
    },
    {
      "id": 79,
      "label": "edge_79",
      "src": 31,
      "dst": 24,
      "weight": 10,
      "bw": 1000000,
      "delay": 127
    },
    {
      "id": 80,
      "label": "edge_80",
      "src": 25,
      "dst": 57,
      "weight": 10,
      "bw": 1000000,
      "delay": 82
    },
    {
      "id": 81,
      "label": "edge_81",
      "src": 57,
      "dst": 25,
      "weight": 10,
      "bw": 1000000,
      "delay": 82
    },
    {
      "id": 82,
      "label": "edge_82",
      "src": 26,
      "dst": 32,
      "weight": 10,
      "bw": 1000000,
      "delay": 338
    },
    {
      "id": 83,
      "label": "edge_83",
      "src": 32,
      "dst": 26,
      "weight": 10,
      "bw": 1000000,
      "delay": 338
    },
    {
      "id": 84,
      "label": "edge_84",
      "src": 27,
      "dst": 30,
      "weight": 10,
      "bw": 1000000,
      "delay": 74
    },
    {
      "id": 85,
      "label": "edge_85",
      "src": 30,
      "dst": 27,
      "weight": 10,
      "bw": 1000000,
      "delay": 74
    },
    {
      "id": 86,
      "label": "edge_86",
      "src": 28,
      "dst": 44,
      "weight": 10,
      "bw": 1000000,
      "delay": 134
    },
    {
      "id": 87,
      "label": "edge_87",
      "src": 44,
      "dst": 28,
      "weight": 10,
      "bw": 1000000,
      "delay": 134
    },
    {
      "id": 88,
      "label": "edge_88",
      "src": 28,
      "dst": 29,
      "weight": 10,
      "bw": 1000000,
      "delay": 87
    },
    {
      "id": 89,
      "label": "edge_89",
      "src": 29,
      "dst": 28,
      "weight": 10,
      "bw": 1000000,
      "delay": 87
    },
    {
      "id": 90,
      "label": "edge_90",
      "src": 29,
      "dst": 31,
      "weight": 10,
      "bw": 1000000,
      "delay": 127
    },
    {
      "id": 91,
      "label": "edge_91",
      "src": 31,
      "dst": 29,
      "weight": 10,
      "bw": 1000000,
      "delay": 127
    },
    {
      "id": 92,
      "label": "edge_92",
      "src": 29,
      "dst": 41,
      "weight": 10,
      "bw": 1000000,
      "delay": 43
    },
    {
      "id": 93,
      "label": "edge_93",
      "src": 41,
      "dst": 29,
      "weight": 10,
      "bw": 1000000,
      "delay": 43
    },
    {
      "id": 94,
      "label": "edge_94",
      "src": 30,
      "dst": 32,
      "weight": 10,
      "bw": 1000000,
      "delay": 58
    },
    {
      "id": 95,
      "label": "edge_95",
      "src": 32,
      "dst": 30,
      "weight": 10,
      "bw": 1000000,
      "delay": 58
    },
    {
      "id": 96,
      "label": "edge_96",
      "src": 32,
      "dst": 54,
      "weight": 10,
      "bw": 1000000,
      "delay": 5
    },
    {
      "id": 97,
      "label": "edge_97",
      "src": 54,
      "dst": 32,
      "weight": 10,
      "bw": 1000000,
      "delay": 5
    },
    {
      "id": 98,
      "label": "edge_98",
      "src": 33,
      "dst": 42,
      "weight": 10,
      "bw": 1000000,
      "delay": 127
    },
    {
      "id": 99,
      "label": "edge_99",
      "src": 42,
      "dst": 33,
      "weight": 10,
      "bw": 1000000,
      "delay": 127
    },
    {
      "id": 100,
      "label": "edge_100",
      "src": 33,
      "dst": 59,
      "weight": 10,
      "bw": 1000000,
      "delay": 127
    },
    {
      "id": 101,
      "label": "edge_101",
      "src": 59,
      "dst": 33,
      "weight": 10,
      "bw": 1000000,
      "delay": 127
    },
    {
      "id": 102,
      "label": "edge_102",
      "src": 33,
      "dst": 60,
      "weight": 10,
      "bw": 1000000,
      "delay": 127
    },
    {
      "id": 103,
      "label": "edge_103",
      "src": 60,
      "dst": 33,
      "weight": 10,
      "bw": 1000000,
      "delay": 127
    },
    {
      "id": 104,
      "label": "edge_104",
      "src": 34,
      "dst": 35,
      "weight": 10,
      "bw": 1000000,
      "delay": 52
    },
    {
      "id": 105,
      "label": "edge_105",
      "src": 35,
      "dst": 34,
      "weight": 10,
      "bw": 1000000,
      "delay": 52
    },
    {
      "id": 106,
      "label": "edge_106",
      "src": 34,
      "dst": 37,
      "weight": 10,
      "bw": 1000000,
      "delay": 75
    },
    {
      "id": 107,
      "label": "edge_107",
      "src": 37,
      "dst": 34,
      "weight": 10,
      "bw": 1000000,
      "delay": 75
    },
    {
      "id": 108,
      "label": "edge_108",
      "src": 36,
      "dst": 39,
      "weight": 10,
      "bw": 1000000,
      "delay": 174
    },
    {
      "id": 109,
      "label": "edge_109",
      "src": 39,
      "dst": 36,
      "weight": 10,
      "bw": 1000000,
      "delay": 174
    },
    {
      "id": 110,
      "label": "edge_110",
      "src": 36,
      "dst": 37,
      "weight": 10,
      "bw": 1000000,
      "delay": 279
    },
    {
      "id": 111,
      "label": "edge_111",
      "src": 37,
      "dst": 36,
      "weight": 10,
      "bw": 1000000,
      "delay": 279
    },
    {
      "id": 112,
      "label": "edge_112",
      "src": 38,
      "dst": 39,
      "weight": 10,
      "bw": 1000000,
      "delay": 23
    },
    {
      "id": 113,
      "label": "edge_113",
      "src": 39,
      "dst": 38,
      "weight": 10,
      "bw": 1000000,
      "delay": 23
    },
    {
      "id": 114,
      "label": "edge_114",
      "src": 38,
      "dst": 41,
      "weight": 10,
      "bw": 1000000,
      "delay": 42
    },
    {
      "id": 115,
      "label": "edge_115",
      "src": 41,
      "dst": 38,
      "weight": 10,
      "bw": 1000000,
      "delay": 42
    },
    {
      "id": 116,
      "label": "edge_116",
      "src": 40,
      "dst": 41,
      "weight": 10,
      "bw": 1000000,
      "delay": 14
    },
    {
      "id": 117,
      "label": "edge_117",
      "src": 41,
      "dst": 40,
      "weight": 10,
      "bw": 1000000,
      "delay": 14
    },
    {
      "id": 118,
      "label": "edge_118",
      "src": 40,
      "dst": 41,
      "weight": 10,
      "bw": 1000000,
      "delay": 14
    },
    {
      "id": 119,
      "label": "edge_119",
      "src": 41,
      "dst": 40,
      "weight": 10,
      "bw": 1000000,
      "delay": 14
    },
    {
      "id": 120,
      "label": "edge_120",
      "src": 42,
      "dst": 43,
      "weight": 10,
      "bw": 1000000,
      "delay": 165
    },
    {
      "id": 121,
      "label": "edge_121",
      "src": 43,
      "dst": 42,
      "weight": 10,
      "bw": 1000000,
      "delay": 165
    },
    {
      "id": 122,
      "label": "edge_122",
      "src": 43,
      "dst": 48,
      "weight": 10,
      "bw": 1000000,
      "delay": 160
    },
    {
      "id": 123,
      "label": "edge_123",
      "src": 48,
      "dst": 43,
      "weight": 10,
      "bw": 1000000,
      "delay": 160
    },
    {
      "id": 124,
      "label": "edge_124",
      "src": 43,
      "dst": 46,
      "weight": 10,
      "bw": 1000000,
      "delay": 135
    },
    {
      "id": 125,
      "label": "edge_125",
      "src": 46,
      "dst": 43,
      "weight": 10,
      "bw": 1000000,
      "delay": 135
    },
    {
      "id": 126,
      "label": "edge_126",
      "src": 44,
      "dst": 48,
      "weight": 10,
      "bw": 1000000,
      "delay": 42
    },
    {
      "id": 127,
      "label": "edge_127",
      "src": 48,
      "dst": 44,
      "weight": 10,
      "bw": 1000000,
      "delay": 42
    },
    {
      "id": 128,
      "label": "edge_128",
      "src": 44,
      "dst": 51,
      "weight": 10,
      "bw": 1000000,
      "delay": 32
    },
    {
      "id": 129,
      "label": "edge_129",
      "src": 51,
      "dst": 44,
      "weight": 10,
      "bw": 1000000,
      "delay": 32
    },
    {
      "id": 130,
      "label": "edge_130",
      "src": 44,
      "dst": 45,
      "weight": 10,
      "bw": 1000000,
      "delay": 104
    },
    {
      "id": 131,
      "label": "edge_131",
      "src": 45,
      "dst": 44,
      "weight": 10,
      "bw": 1000000,
      "delay": 104
    },
    {
      "id": 132,
      "label": "edge_132",
      "src": 45,
      "dst": 46,
      "weight": 10,
      "bw": 1000000,
      "delay": 135
    },
    {
      "id": 133,
      "label": "edge_133",
      "src": 46,
      "dst": 45,
      "weight": 10,
      "bw": 1000000,
      "delay": 135
    },
    {
      "id": 134,
      "label": "edge_134",
      "src": 46,
      "dst": 47,
      "weight": 10,
      "bw": 1000000,
      "delay": 72
    },
    {
      "id": 135,
      "label": "edge_135",
      "src": 47,
      "dst": 46,
      "weight": 10,
      "bw": 1000000,
      "delay": 72
    },
    {
      "id": 136,
      "label": "edge_136",
      "src": 48,
      "dst": 49,
      "weight": 10,
      "bw": 1000000,
      "delay": 72
    },
    {
      "id": 137,
      "label": "edge_137",
      "src": 49,
      "dst": 48,
      "weight": 10,
      "bw": 1000000,
      "delay": 72
    },
    {
      "id": 138,
      "label": "edge_138",
      "src": 48,
      "dst": 58,
      "weight": 10,
      "bw": 1000000,
      "delay": 339
    },
    {
      "id": 139,
      "label": "edge_139",
      "src": 58,
      "dst": 48,
      "weight": 10,
      "bw": 1000000,
      "delay": 339
    },
    {
      "id": 140,
      "label": "edge_140",
      "src": 49,
      "dst": 50,
      "weight": 10,
      "bw": 1000000,
      "delay": 69
    },
    {
      "id": 141,
      "label": "edge_141",
      "src": 50,
      "dst": 49,
      "weight": 10,
      "bw": 1000000,
      "delay": 69
    },
    {
      "id": 142,
      "label": "edge_142",
      "src": 50,
      "dst": 51,
      "weight": 10,
      "bw": 1000000,
      "delay": 130
    },
    {
      "id": 143,
      "label": "edge_143",
      "src": 51,
      "dst": 50,
      "weight": 10,
      "bw": 1000000,
      "delay": 130
    },
    {
      "id": 144,
      "label": "edge_144",
      "src": 52,
      "dst": 53,
      "weight": 10,
      "bw": 1000000,
      "delay": 121
    },
    {
      "id": 145,
      "label": "edge_145",
      "src": 53,
      "dst": 52,
      "weight": 10,
      "bw": 1000000,
      "delay": 121
    },
    {
      "id": 146,
      "label": "edge_146",
      "src": 52,
      "dst": 60,
      "weight": 10,
      "bw": 1000000,
      "delay": 178
    },
    {
      "id": 147,
      "label": "edge_147",
      "src": 60,
      "dst": 52,
      "weight": 10,
      "bw": 1000000,
      "delay": 178
    },
    {
      "id": 148,
      "label": "edge_148",
      "src": 54,
      "dst": 55,
      "weight": 10,
      "bw": 1000000,
      "delay": 88
    },
    {
      "id": 149,
      "label": "edge_149",
      "src": 55,
      "dst": 54,
      "weight": 10,
      "bw": 1000000,
      "delay": 88
    },
    {
      "id": 150,
      "label": "edge_150",
      "src": 55,
      "dst": 56,
      "weight": 10,
      "bw": 1000000,
      "delay": 92
    },
    {
      "id": 151,
      "label": "edge_151",
      "src": 56,
      "dst": 55,
      "weight": 10,
      "bw": 1000000,
      "delay": 92
    },
    {
      "id": 152,
      "label": "edge_152",
      "src": 56,
      "dst": 57,
      "weight": 10,
      "bw": 1000000,
      "delay": 35
    },
    {
      "id": 153,
      "label": "edge_153",
      "src": 57,
      "dst": 56,
      "weight": 10,
      "bw": 1000000,
      "delay": 35
    },
    {
      "id": 154,
      "label": "edge_154",
      "src": 57,
      "dst": 58,
      "weight": 10,
      "bw": 1000000,
      "delay": 161
    },
    {
      "id": 155,
      "label": "edge_155",
      "src": 58,
      "dst": 57,
      "weight": 10,
      "bw": 1000000,
      "delay": 161
    },
    {
      "id": 156,
      "label": "edge_156",
      "src": 58,
      "dst": 59,
      "weight": 10,
      "bw": 1000000,
      "delay": 264
    },
    {
      "id": 157,
      "label": "edge_157",
      "src": 59,
      "dst": 58,
      "weight": 10,
      "bw": 1000000,
      "delay": 264
    }
  ]
}